shipyard_googlesheets/__init__.py
shipyard_googlesheets/exceptions.py
shipyard_googlesheets/googlesheets.py
shipyard_googlesheets/cli/__init__.py
shipyard_googlesheets/cli/authtest.py
shipyard_googlesheets/cli/clear_data.py
shipyard_googlesheets/cli/download.py
shipyard_googlesheets/cli/upload.py
shipyard_googlesheets-0.4.1.dist-info/METADATA
shipyard_googlesheets-0.4.1.dist-info/WHEEL
shipyard_googlesheets-0.4.1.dist-info/top_level.txt
shipyard_googlesheets-0.4.1.dist-info/RECORD
